easing_functions/__init__.py
easing_functions/easing.py
easing_functions-1.0.4.dist-info/LICENCE.md
easing_functions-1.0.4.dist-info/METADATA
easing_functions-1.0.4.dist-info/WHEEL
easing_functions-1.0.4.dist-info/top_level.txt
easing_functions-1.0.4.dist-info/RECORD
