Metadata-Version: 2.1
Name: easing-functions
Version: 1.0.4
Summary: A collection of the basic easing functions for python
Home-page: https://github.com/semitable/easing-functions
Author: Filippos Christianos
Author-email: almak72@gmail.com
License: GPL 3.0
Platform: UNKNOWN
Classifier: Programming Language :: Python :: 3
Classifier: Development Status :: 5 - Production/Stable
Classifier: Operating System :: OS Independent
